setup.py
isonline/__init__.py
isonline/auto.py
isonline.egg-info/PKG-INFO
isonline.egg-info/SOURCES.txt
isonline.egg-info/dependency_links.txt
isonline.egg-info/entry_points.txt
isonline.egg-info/not-zip-safe
isonline.egg-info/pbr.json
isonline.egg-info/requires.txt
isonline.egg-info/top_level.txt