Metadata-Version: 1.0
Name: isonline
Version: 1.0.0
Summary: Check if the internet connection is up
Home-page: http://github.com/akashnimare/isonline/
Author: Akash Nimare
Author-email: svnitakash@gmail.com
License: MIT
Keywords: website status website down website up internet check command line too
Platform: UNKNOWN
